setup.py
bin/librato-macos
librato_macos/__init__.py
librato_macos.egg-info/PKG-INFO
librato_macos.egg-info/SOURCES.txt
librato_macos.egg-info/dependency_links.txt
librato_macos.egg-info/not-zip-safe
librato_macos.egg-info/requires.txt
librato_macos.egg-info/top_level.txt