Metadata-Version: 1.0
Name: librato-macos
Version: 0.1.3
Summary: A library to submit measurements to Librato for a MAC OS instance
Home-page: http://www.librato.com
Author: librato
Author-email: support@librato.com
License: MIT
Platform: UNKNOWN
